__init__.py
tmc2gmns.py
tmc2gmns-0.1.5.dist-info/LICENSE
tmc2gmns-0.1.5.dist-info/METADATA
tmc2gmns-0.1.5.dist-info/WHEEL
tmc2gmns-0.1.5.dist-info/top_level.txt
tmc2gmns-0.1.5.dist-info/RECORD
