Metadata-Version: 2.1
Name: tmc2gmns
Version: 0.1.5
Summary: An open-source python package converting TMC data into GMNS format.
Home-page: https://github.com/vegampire/TMC2GMNS
Author: Dr. Xuesong Zhou, Xianbiao Hu, Jiawei Lu, Chris Yang Song
Author-email: xzhou74@asu.edu, xbhu@mst.edu, jiaweil9@asu.edu, 845107945@qq.com
License: UNKNOWN
Platform: UNKNOWN
Classifier: Programming Language :: Python :: 3
Classifier: License :: OSI Approved :: MIT License
Classifier: Operating System :: OS Independent
License-File: LICENSE
Requires-Dist: osm2gmns (>=0.5.2)
Requires-Dist: numpy (>=1.19.2)
Requires-Dist: pandas (>=1.1.3)
Requires-Dist: MapMatching4GMNS (>=0.2.11)
